[
  {
    "name": "LabAdminDashboard.backup.jsx",
    "size": 227492
  },
  {
    "name": "LabAdminDashboard.css",
    "size": 27175
  },
  {
    "name": "LabAdminDashboard.css.bak",
    "size": 54346
  },
  {
    "name": "LabAdminDashboard.css.bak.utf8.css",
    "size": 27177
  },
  {
    "name": "LabAdminDashboard.css.bak_utf8.css",
    "size": 27175
  },
  {
    "name": "LabAdminDashboard.jsx",
    "size": 249706
  },
  {
    "name": "LabAdminDashboard.temp.jsx",
    "size": 227492
  },
  {
    "name": "LabAdminDashboard.utf8.jsx",
    "size": 114004
  },
  {
    "name": "LabAdminDashboard_backup_temp.jsx",
    "size": 114006
  },
  {
    "name": "LabAdminDashboard_cecb037.jsx",
    "size": 499136
  },
  {
    "name": "LabAdminDashboard_cecb037_utf8.jsx",
    "size": 249706
  },
  {
    "name": "LabAdminDashboard_old.jsx",
    "size": 440978
  },
  {
    "name": "LabAdminDashboard_old_utf8.jsx",
    "size": 220612
  }
]